README.md
setup.cfg
setup.py
RedisLibrary/RedisLibraryKeywords.py
RedisLibrary/__init__.py
RedisLibrary/version.py
robotframework_redislibrary_xwfintech.egg-info/PKG-INFO
robotframework_redislibrary_xwfintech.egg-info/SOURCES.txt
robotframework_redislibrary_xwfintech.egg-info/dependency_links.txt
robotframework_redislibrary_xwfintech.egg-info/not-zip-safe
robotframework_redislibrary_xwfintech.egg-info/requires.txt
robotframework_redislibrary_xwfintech.egg-info/top_level.txt