Metadata-Version: 1.1
Name: robotframework-redislibrary-xwfintech
Version: 0.4
Summary: robotframework-redislibrary is a Robot Framework test library for manipulating in-memory data which store in Redis
Home-page: https://github.com/houfy-github/robotframework-redislibrary.git
Author: Traitanit Huangsri
Author-email: traitanit.hua@gmail.com
License: UNKNOWN
Keywords: robotframework redislibrary redis
Platform: UNKNOWN
Classifier: Development Status :: 5 - Production/Stable
Classifier: License :: Public Domain
Classifier: Operating System :: OS Independent
Classifier: Programming Language :: Python
Classifier: Topic :: Software Development :: Testing
